README.md
setup.py
ergaleia/__init__.py
ergaleia/config.py
ergaleia/from_xml.py
ergaleia/import_by_path.py
ergaleia/load_from_path.py
ergaleia/nested_get.py
ergaleia/normalize_path.py
ergaleia/to_args.py
ergaleia/un_comment.py
ergaleia.egg-info/PKG-INFO
ergaleia.egg-info/SOURCES.txt
ergaleia.egg-info/dependency_links.txt
ergaleia.egg-info/top_level.txt