Metadata-Version: 1.0
Name: ergaleia
Version: 1.3.2
Summary: A library of random tools
Home-page: https://github.com/robertchase/ergaleia
Author: Bob Chase
Author-email: UNKNOWN
License: MIT
Platform: UNKNOWN
